Week 3/Structural/2bitadder.v
module bit2adder(a,b,sum,cout,cin);
    input  [1:0]a,b; 
    input  cin;
    output [1:0]sum;
    output cout;
    wire  w,w1,w2,w3,w4,w5,w6,w7,w8,w9;
// sum's first digit
    xor xor1(w,a[0],b[0]);
    xor xor2(sum[0],w,cin);

// carry of first 1 bit adder
    and and1(w1,a[0],b[0]);
    and and2(w2,b[0],cin);
    and and3(w3,a[0],cin);

    or or1(w4,w1,w2);
    or or2(w5,w4,w3);

// sum of 2nd digit
    xor xor3(w6,a[1],b[1]);
    xor xor4(sum[1],w6,w5);
// cout 
    and and4(w7,a[1],b[1]);
    and and5(w8,b[1],w5);
    and and6(w9,a[1],w5);

    or or3(w10,w7,w8);
    or or4(cout,w10,w9);


endmodule

Week 3/Structural/2bitadder_tb.v
`include "2bitadder.v"

module bit2adder_tb;

reg [1:0]a,b;
reg cin;
integer i;
wire [1:0] sum;
wire  cout;

bit2adder uut(a,b,sum,cout,cin);

initial begin
    $dumpfile("bit2adder_tb.vcd");
    $dumpvars(0,bit2adder_tb);
    
    $monitor($time , "a = %2b b = %2b cin = %1b sum = %2b cout=%1b",a,b,cin,sum,cout);
    for(i=0 ; i<32 ; i=i+1) begin
        #10 {a,b,cin} = i;
    end
    #100 $finish;
end

endmodule

Week 3/Structural/bit2adder_tb.vcd
$date
	Tue Nov 01 17:26:50 2022
$end
$version
	Icarus Verilog
$end
$timescale
	1s
$end
$scope module bit2adder_tb $end
$var wire 2 ! sum [1:0] $end
$var wire 1 " cout $end
$var reg 2 # a [1:0] $end
$var reg 2 $ b [1:0] $end
$var reg 1 % cin $end
$var integer 32 & i [31:0] $end
$scope module uut $end
$var wire 2 ' a [1:0] $end
$var wire 2 ( b [1:0] $end
$var wire 1 % cin $end
$var wire 1 " cout $end
$var wire 1 ) w $end
$var wire 1 * w1 $end
$var wire 1 + w10 $end
$var wire 1 , w2 $end
$var wire 1 - w3 $end
$var wire 1 . w4 $end
$var wire 1 / w5 $end
$var wire 1 0 w6 $end
$var wire 1 1 w7 $end
$var wire 1 2 w8 $end
$var wire 1 3 w9 $end
$var wire 2 4 sum [1:0] $end
$upscope $end
$upscope $end
$enddefinitions $end
$comment Show the parameter values. $end
$dumpall
$end
#0
$dumpvars
bx 4
x3
x2
x1
x0
x/
x.
x-
x,
x+
x*
x)
bx (
bx '
b0 &
x%
bx $
bx #
x"
bx !
$end
#10
0/
0"
b0 !
b0 4
0.
0+
03
0)
0*
00
01
02
0,
0-
b1 &
b0 #
b0 '
b0 $
b0 (
0%
#20
b1 !
b1 4
b10 &
1%
#30
1)
b1 !
b1 4
b11 &
b1 $
b1 (
0%
#40
1/
1.
b10 !
b10 4
1,
b100 &
1%
#50
0"
0+
0/
0)
10
02
0.
b10 !
b10 4
0,
b101 &
b10 $
b10 (
0%
#60
b11 !
b11 4
b110 &
1%
#70
1)
b11 !
b11 4
b111 &
b11 $
b11 (
0%
#80
1"
1+
12
1/
1.
b0 !
b0 4
1,
b1000 &
1%
#90
0"
0+
0/
00
02
0.
b1 !
b1 4
0,
b1001 &
b1 #
b1 '
b0 $
b0 (
0%
#100
1/
b10 !
b10 4
1-
b1010 &
1%
#110
1.
0)
1*
1/
b10 !
b10 4
0-
b1011 &
b1 $
b1 (
0%
#120
b11 !
b11 4
1,
1-
b1100 &
1%
#130
0/
0"
0.
0+
1)
0*
10
02
b11 !
b11 4
0,
0-
b1101 &
b10 $
b10 (
0%
#140
1"
1+
12
1/
b0 !
b0 4
1-
b1110 &
1%
#150
1"
1+
1.
12
0)
1*
1/
b0 !
b0 4
0-
b1111 &
b11 $
b11 (
0%
#160
b1 !
b1 4
1,
1-
b10000 &
1%
#170
0"
0/
0.
0+
03
0*
02
b10 !
b10 4
0,
0-
b10001 &
b10 #
b10 '
b0 $
b0 (
0%
#180
b11 !
b11 4
b10010 &
1%
#190
1)
b11 !
b11 4
b10011 &
b1 $
b1 (
0%
#200
1"
13
1/
1.
b0 !
b0 4
1,
b10100 &
1%
#210
03
1+
0/
0)
00
11
02
0.
b0 !
b0 4
0,
b10101 &
b10 $
b10 (
0%
#220
b1 !
b1 4
b10110 &
1%
#230
1)
b1 !
b1 4
b10111 &
b11 $
b11 (
0%
#240
12
13
1/
1.
b10 !
b10 4
1,
b11000 &
1%
#250
0"
03
0+
0/
10
01
02
0.
b11 !
b11 4
0,
b11001 &
b11 #
b11 '
b0 $
b0 (
0%
#260
1"
13
1/
b0 !
b0 4
1-
b11010 &
1%
#270
1"
1.
13
0)
1*
1/
b0 !
b0 4
0-
b11011 &
b1 $
b1 (
0%
#280
b1 !
b1 4
1,
1-
b11100 &
1%
#290
03
0/
0.
1+
1)
0*
00
11
02
b1 !
b1 4
0,
0-
b11101 &
b10 $
b10 (
0%
#300
12
13
1/
b10 !
b10 4
1-
b11110 &
1%
#310
1.
12
13
0)
1*
1/
b10 !
b10 4
0-
b11111 &
b11 $
b11 (
0%
#320
b11 !
b11 4
1,
1-
b100000 &
1%
