Week4/Mux/Mux.v
module Mux (S,D0,D1,Y);
    input S , D0 , D1;
    output Y;
    wire w1;

    not not1(w1,S);
    assign Y = (S & D1) | (w1 & D0);
    
endmodule

Week4/Mux/Mux_tb.v
module Mux_tb ;

    reg S,D0,D1;
    wire Y;
    integer i;
    
    
        

    Mux uut(S,D0,D1,Y);
    initial begin

    $dumpfile("Mux_tb.vcd");
    $dumpvars(0,Mux_tb);

    $monitor($time , "S=%b D0=%b D1=%b Y=%b" , S,D0,D1,Y);

    for (i=0 ; i<8 ; i=i+1) begin
        #10 {S,D0,D1} = i;
    end
    #100 $finish;
    end
    
endmodule

Week4/Mux/Mux_tb.vcd
$date
	Thu Nov 03 22:13:46 2022
$end
$version
	Icarus Verilog
$end
$timescale
	1s
$end
$scope module Mux_tb $end
$var wire 1 ! Y $end
$var reg 1 " D0 $end
$var reg 1 # D1 $end
$var reg 1 $ S $end
$var integer 32 % i [31:0] $end
$scope module uut $end
$var wire 1 " D0 $end
$var wire 1 # D1 $end
$var wire 1 $ S $end
$var wire 1 ! Y $end
$var wire 1 & w1 $end
$upscope $end
$upscope $end
$enddefinitions $end
$comment Show the parameter values. $end
$dumpall
$end
#0
$dumpvars
x&
b0 %
x$
x#
x"
x!
$end
#10
0!
1&
b1 %
0$
0"
0#
#20
b10 %
1#
#30
1!
b11 %
1"
0#
#40
b100 %
1#
#50
0!
0&
b101 %
1$
0"
0#
#60
1!
b110 %
1#
#70
0!
b111 %
1"
0#
#80
1!
b1000 %
1#
