Week4/Boolean/Boolean.v
module Boolean (x,a,b,c);
    input  a,b,c;
    output x;

    assign x= a&b | a&c | a&b&c ;

endmodule

Week4/Boolean/Boolean_tb.v
module Boolean_tb;

    reg a,b,c;
    wire x;
    integer i;

    Boolean uut(x,a,b,c);

    initial  begin

    $dumpfile("Boolean_tb.vcd");
    $dumpvars(0,Boolean_tb);

    $monitor ($time , "a = %b b=%b c=%b x=%b",a,b,c,x);

    for (i=0 ; i<8 ;i=i+1) begin
        #10 {a,b,c} = i;
    end
    #100 $finish;

    end

endmodule

Week4/Boolean/Boolean_tb.vcd
$date
	Thu Nov 03 00:48:30 2022
$end
$version
	Icarus Verilog
$end
$timescale
	1s
$end
$scope module Boolean_tb $end
$var wire 1 ! x $end
$var reg 1 " a $end
$var reg 1 # b $end
$var reg 1 $ c $end
$var integer 32 % i [31:0] $end
$scope module uut $end
$var wire 1 " a $end
$var wire 1 # b $end
$var wire 1 $ c $end
$var wire 1 ! x $end
$upscope $end
$upscope $end
$enddefinitions $end
$comment Show the parameter values. $end
$dumpall
$end
#0
$dumpvars
b0 %
x$
x#
x"
x!
$end
#10
0!
b1 %
0"
0#
0$
#20
b10 %
1$
#30
b11 %
1#
0$
#40
b100 %
1$
#50
b101 %
1"
0#
0$
#60
1!
b110 %
1$
#70
b111 %
1#
0$
#80
b1000 %
1$
